MANIFEST.in
README.md
setup.py
nlpcda/__init__.py
nlpcda/config.py
nlpcda/example.py
nlpcda.egg-info/PKG-INFO
nlpcda.egg-info/SOURCES.txt
nlpcda.egg-info/dependency_links.txt
nlpcda.egg-info/requires.txt
nlpcda.egg-info/top_level.txt
nlpcda/data/company.txt
nlpcda/data/同义词.txt
nlpcda/data/同音意字.txt
nlpcda/tools/Basetool.py
nlpcda/tools/Char_position_exchange.py
nlpcda/tools/Homophone.py
nlpcda/tools/Ner.py
nlpcda/tools/Random_delete_char.py
nlpcda/tools/Random_word.py
nlpcda/tools/Similar_word.py
nlpcda/tools/__init__.py
nlpcda/tools/homophone.py
nlpcda/tools/ner.py