Metadata-Version: 2.1
Name: nlpcda
Version: 2.2.0
Summary: NLP Chinese Data Augmentation.一键中文数据增强.NLP数据增强
Home-page: https://github.com/425776024/nlpcda
Author: Jiang.XinFa
Author-email: 425776024@qq.com
License: MIT Licence
Keywords: pip,nlptool,nlpcda,nlp,
Platform: any
